Workbook

Sheet Company Data
A1: Comparable Company Analysis — UBER
A2: Source: Yahoo Finance, StockAnalysis, Company Filings (Feb 2026)
A4: Company | B4: Ticker | C4: Exchange | D4: Stock Price ($) | E4: Shares Out (M) | F4: Market Cap ($M) | G4: Cash ($M) | H4: Total Debt ($M) | I4: Enterprise Value ($M) | J4: Revenue TTM ($M) | K4: EBITDA TTM ($M) | L4: Net Income TTM ($M) | M4: Book Value ($M)
A5: Uber Technologies | B5: UBER | C5: NYSE | D5: 72.83 | E5: 2084 | F5: =D5*E5 | G5: 7000 | H5: 9800 | I5: =F5+H5-G5 | J5: 52020 | K5: 6310 | L5: 10050 | M5: 28100
A6: DoorDash | B6: DASH | C6: NASDAQ | D6: 185 | E6: 405 | F6: =D6*E6 | G6: 4600 | H6: 2500 | I6: =F6+H6-G6 | J6: 13700 | K6: 1300 | L6: 500 | M6: 7800
A7: Lyft | B7: LYFT | C7: NASDAQ | D7: 13.5 | E7: 395 | F7: =D7*E7 | G7: 1800 | H7: 1400 | I7: =F7+H7-G7 | J7: 6300 | K7: 529 | L7: 300 | M7: 2200
A8: Grab Holdings | B8: GRAB | C8: NASDAQ | D8: 4.2 | E8: 3950 | F8: =D8*E8 | G8: 5000 | H8: 1200 | I8: =F8+H8-G8 | J8: 3200 | K8: 490 | L8: -100 | M8: 8500
A9: Deliveroo | B9: ROO | C9: LSE | D9: 1.5 | E9: 1800 | F9: =D9*E9 | G9: 600 | H9: 200 | I9: =F9+H9-G9 | J9: 2600 | K9: 120 | L9: -50 | M9: 1200
A10: Just Eat Takeaway | B10: TKWY | C10: Euronext | D10: 17 | E10: 220 | F10: =D10*E10 | G10: 800 | H10: 1200 | I10: =F10+H10-G10 | J10: 3700 | K10: 300 | L10: -200 | M10: 3000
A11: Instacart | B11: CART | C11: NASDAQ | D11: 28 | E11: 290 | F11: =D11*E11 | G11: 2100 | H11: 400 | I11: =F11+H11-G11 | J11: 3400 | K11: 850 | L11: 600 | M11: 3500

Sheet Trading Multiples
A1: Trading Multiples — UBER vs Peers
A3: Company | B3: Ticker | C3: EV/Revenue | D3: EV/EBITDA | E3: P/E | F3: P/Book | G3: Revenue Gr. YoY | H3: EBITDA Margin | I3: Net Margin | J3: ROE
A4: ='Company Data'!A5 | B4: ='Company Data'!B5 | C4: ='Company Data'!I5/'Company Data'!J5 | D4: ='Company Data'!I5/'Company Data'!K5 | E4: ='Company Data'!F5/'Company Data'!L5 | F4: ='Company Data'!F5/'Company Data'!M5 | G4: 0.183 | H4: ='Company Data'!K5/'Company Data'!J5 | I4: ='Company Data'!L5/'Company Data'!J5 | J4: ='Company Data'!L5/'Company Data'!M5
A5: ='Company Data'!A6 | B5: ='Company Data'!B6 | C5: ='Company Data'!I6/'Company Data'!J6 | D5: ='Company Data'!I6/'Company Data'!K6 | E5: ='Company Data'!F6/'Company Data'!L6 | F5: ='Company Data'!F6/'Company Data'!M6 | G5: 0.38 | H5: ='Company Data'!K6/'Company Data'!J6 | I5: ='Company Data'!L6/'Company Data'!J6 | J5: ='Company Data'!L6/'Company Data'!M6
A6: ='Company Data'!A7 | B6: ='Company Data'!B7 | C6: ='Company Data'!I7/'Company Data'!J7 | D6: ='Company Data'!I7/'Company Data'!K7 | E6: ='Company Data'!F7/'Company Data'!L7 | F6: ='Company Data'!F7/'Company Data'!M7 | G6: 0.14 | H6: ='Company Data'!K7/'Company Data'!J7 | I6: ='Company Data'!L7/'Company Data'!J7 | J6: ='Company Data'!L7/'Company Data'!M7
A7: ='Company Data'!A8 | B7: ='Company Data'!B8 | C7: ='Company Data'!I8/'Company Data'!J8 | D7: ='Company Data'!I8/'Company Data'!K8 | E7: ='Company Data'!F8/'Company Data'!L8 | F7: ='Company Data'!F8/'Company Data'!M8 | G7: 0.17 | H7: ='Company Data'!K8/'Company Data'!J8 | I7: ='Company Data'!L8/'Company Data'!J8 | J7: ='Company Data'!L8/'Company Data'!M8
A8: ='Company Data'!A9 | B8: ='Company Data'!B9 | C8: ='Company Data'!I9/'Company Data'!J9 | D8: ='Company Data'!I9/'Company Data'!K9 | E8: ='Company Data'!F9/'Company Data'!L9 | F8: ='Company Data'!F9/'Company Data'!M9 | G8: 0.1 | H8: ='Company Data'!K9/'Company Data'!J9 | I8: ='Company Data'!L9/'Company Data'!J9 | J8: ='Company Data'!L9/'Company Data'!M9
A9: ='Company Data'!A10 | B9: ='Company Data'!B10 | C9: ='Company Data'!I10/'Company Data'!J10 | D9: ='Company Data'!I10/'Company Data'!K10 | E9: ='Company Data'!F10/'Company Data'!L10 | F9: ='Company Data'!F10/'Company Data'!M10 | G9: -0.05 | H9: ='Company Data'!K10/'Company Data'!J10 | I9: ='Company Data'!L10/'Company Data'!J10 | J9: ='Company Data'!L10/'Company Data'!M10
A10: ='Company Data'!A11 | B10: ='Company Data'!B11 | C10: ='Company Data'!I11/'Company Data'!J11 | D10: ='Company Data'!I11/'Company Data'!K11 | E10: ='Company Data'!F11/'Company Data'!L11 | F10: ='Company Data'!F11/'Company Data'!M11 | G10: 0.15 | H10: ='Company Data'!K11/'Company Data'!J11 | I10: ='Company Data'!L11/'Company Data'!J11 | J10: ='Company Data'!L11/'Company Data'!M11
A12: Median | C12: =MEDIAN(C4:C10) | D12: =MEDIAN(D4:D10) | E12: =MEDIAN(E4:E10) | F12: =MEDIAN(F4:F10) | G12: =MEDIAN(G4:G10) | H12: =MEDIAN(H4:H10) | I12: =MEDIAN(I4:I10) | J12: =MEDIAN(J4:J10)
A13: Mean | C13: =AVERAGE(C4:C10) | D13: =AVERAGE(D4:D10) | E13: =AVERAGE(E4:E10) | F13: =AVERAGE(F4:F10) | G13: =AVERAGE(G4:G10) | H13: =AVERAGE(H4:H10) | I13: =AVERAGE(I4:I10) | J13: =AVERAGE(J4:J10)
A14: Min | C14: =MIN(C4:C10) | D14: =MIN(D4:D10) | E14: =MIN(E4:E10) | F14: =MIN(F4:F10) | G14: =MIN(G4:G10) | H14: =MIN(H4:H10) | I14: =MIN(I4:I10) | J14: =MIN(J4:J10)
A15: Max | C15: =MAX(C4:C10) | D15: =MAX(D4:D10) | E15: =MAX(E4:E10) | F15: =MAX(F4:F10) | G15: =MAX(G4:G10) | H15: =MAX(H4:H10) | I15: =MAX(I4:I10) | J15: =MAX(J4:J10)
A17: Implied Valuation for UBER
A18: Method | B18: Multiple Applied | C18: UBER Metric ($M) | D18: Implied EV/Equity ($M) | E18: Implied Price/Share ($)
A19: EV/Revenue (Median) | B19: =C12 | C19: ='Company Data'!J5 | D19: =B19*C19 | E19: =(D19-'Company Data'!H5+'Company Data'!G5)/'Company Data'!E5
A20: EV/EBITDA (Median) | B20: =D12 | C20: ='Company Data'!K5 | D20: =B20*C20 | E20: =(D20-'Company Data'!H5+'Company Data'!G5)/'Company Data'!E5
A21: P/E (Median) | B21: =E12 | C21: ='Company Data'!L5 | D21: =B21*C21 | E21: =D21/'Company Data'!E5
