Workbook

Sheet Assumptions
A1: DCF Model — UBER (Uber Technologies)
A3: Key Assumptions
A4: Current Stock Price ($) | B4: 72.83
A5: Shares Outstanding (M) | B5: 2084
A7: Risk-Free Rate (10Y UST) | B7: 0.043
A8: Equity Risk Premium | B8: 0.055
A9: Country Risk Premium | B9: 0.005
A10: Levered Beta | B10: 1.15
A11: Cost of Equity | B11: =B7+B10*(B8+B9)
A13: Pre-Tax Cost of Debt | B13: 0.055
A14: Tax Rate | B14: 0.21
A15: After-Tax Cost of Debt | B15: =B13*(1-B14)
A17: Market Cap ($M) | B17: =B4*B5
A18: Total Debt ($M) | B18: 9800
A19: Cash ($M) | B19: 7000
A20: Enterprise Value ($M) | B20: =B17+B18-B19
A21: Debt Weight | B21: =B18/(B17+B18)
A22: Equity Weight | B22: =B17/(B17+B18)
A23: WACC | B23: =B22*B11+B21*B15
A25: Terminal Growth Rate (Base) | B25: 0.03
A26: Exit EV/EBITDA Multiple (Base) | B26: 20
A28: Revenue Growth Assumptions
B29: 2025A | C29: 2026E | D29: 2027E | E29: 2028E | F29: 2029E | G29: 2030E
A30: Revenue Growth Rate | B30: 0.183 | C30: 0.17 | D30: 0.15 | E30: 0.13 | F30: 0.11 | G30: 0.1
A31: EBITDA Margin | B31: 0.121 | C31: 0.155 | D31: 0.175 | E31: 0.195 | F31: 0.21 | G31: 0.22
A32: Capex % of Revenue | B32: 0.035 | C32: 0.035 | D32: 0.03 | E32: 0.03 | F32: 0.025 | G32: 0.025
A33: D&A % of Revenue | B33: 0.025 | C33: 0.025 | D33: 0.025 | E33: 0.025 | F33: 0.025 | G33: 0.025
A34: Change in WC % of Rev | B34: 0.01 | C34: 0.01 | D34: 0.01 | E34: 0.008 | F34: 0.008 | G34: 0.005

Sheet FCF Projections
A1: Free Cash Flow Projections — UBER
B3: 2025A | C3: 2026E | D3: 2027E | E3: 2028E | F3: 2029E | G3: 2030E
A4: Revenue ($M) | B4: 52020 | C4: =B4*(1+Assumptions!C30) | D4: =C4*(1+Assumptions!D30) | E4: =D4*(1+Assumptions!E30) | F4: =E4*(1+Assumptions!F30) | G4: =F4*(1+Assumptions!G30)
A5: Growth % | B5: =Assumptions!B30 | C5: =Assumptions!C30 | D5: =Assumptions!D30 | E5: =Assumptions!E30 | F5: =Assumptions!F30 | G5: =Assumptions!G30
A7: EBITDA ($M) | B7: 6310 | C7: =C4*Assumptions!C31 | D7: =D4*Assumptions!D31 | E7: =E4*Assumptions!E31 | F7: =F4*Assumptions!F31 | G7: =G4*Assumptions!G31
A8: EBITDA Margin | B8: =B7/B4 | C8: =C7/C4 | D8: =D7/D4 | E8: =E7/E4 | F8: =F7/F4 | G8: =G7/G4
A9: (-) D&A ($M) | C9: =C4*Assumptions!C33 | D9: =D4*Assumptions!D33 | E9: =E4*Assumptions!E33 | F9: =F4*Assumptions!F33 | G9: =G4*Assumptions!G33
A10: EBIT ($M) | C10: =C7-C9 | D10: =D7-D9 | E10: =E7-E9 | F10: =F7-F9 | G10: =G7-G9
A11: (-) Taxes on EBIT ($M) | C11: =C10*Assumptions!B14 | D11: =D10*Assumptions!B14 | E11: =E10*Assumptions!B14 | F11: =F10*Assumptions!B14 | G11: =G10*Assumptions!B14
A12: NOPAT ($M) | C12: =C10-C11 | D12: =D10-D11 | E12: =E10-E11 | F12: =F10-F11 | G12: =G10-G11
A14: (-) Capex ($M) | C14: =C4*Assumptions!C32 | D14: =D4*Assumptions!D32 | E14: =E4*Assumptions!E32 | F14: =F4*Assumptions!F32 | G14: =G4*Assumptions!G32
A15: (-) Change in WC ($M) | C15: =C4*Assumptions!C34 | D15: =D4*Assumptions!D34 | E15: =E4*Assumptions!E34 | F15: =F4*Assumptions!F34 | G15: =G4*Assumptions!G34
A16: (+) D&A ($M) | C16: =C9 | D16: =D9 | E16: =E9 | F16: =F9 | G16: =G9
A17: Unlevered FCF ($M) | C17: =C12-C14-C15+C16 | D17: =D12-D14-D15+D16 | E17: =E12-E14-E15+E16 | F17: =F12-F14-F15+F16 | G17: =G12-G14-G15+G16

Sheet Valuation
A1: DCF Valuation — UBER
A3: Present Value of Free Cash Flows
B4: 2026E | C4: 2027E | D4: 2028E | E4: 2029E | F4: 2030E
A5: UFCF ($M) | B5: ='FCF Projections'!C17 | C5: ='FCF Projections'!D17 | D5: ='FCF Projections'!E17 | E5: ='FCF Projections'!F17 | F5: ='FCF Projections'!G17
A6: Discount Factor | B6: =1/(1+Assumptions!B23)^1 | C6: =1/(1+Assumptions!B23)^2 | D6: =1/(1+Assumptions!B23)^3 | E6: =1/(1+Assumptions!B23)^4 | F6: =1/(1+Assumptions!B23)^5
A7: PV of FCF ($M) | B7: =B5*B6 | C7: =C5*C6 | D7: =D5*D6 | E7: =E5*E6 | F7: =F5*F6
A9: Sum of PV of FCFs ($M) | B9: =SUM(B7:F7)
A11: Terminal Value
A12: Method 1: Perpetuity Growth
A13: Terminal FCF (2030E) | B13: ='FCF Projections'!G17
A14: Terminal Growth Rate | B14: =Assumptions!B25
A15: Terminal Value (Perpetuity) | B15: =B13*(1+B14)/(Assumptions!B23-B14)
A16: PV of Terminal Value | B16: =B15/(1+Assumptions!B23)^5
A18: Method 2: Exit Multiple
A19: Terminal EBITDA (2030E) | B19: ='FCF Projections'!G7
A20: Exit EV/EBITDA Multiple | B20: =Assumptions!B26
A21: Terminal Value (Exit Multiple) | B21: =B19*B20
A22: PV of Terminal Value | B22: =B21/(1+Assumptions!B23)^5
A24: Implied Valuation
B25: Perpetuity Method | C25: Exit Multiple Method | D25: Blended (50/50)
A26: Sum of PV of FCFs | B26: =B9 | C26: =B9 | D26: =B9
A27: PV of Terminal Value | B27: =B16 | C27: =B22 | D27: =(B16+B22)/2
A28: Enterprise Value ($M) | B28: =B26+B27 | C28: =C26+C27 | D28: =D26+D27
A29: (-) Net Debt ($M) | B29: =Assumptions!B18-Assumptions!B19 | C29: =Assumptions!B18-Assumptions!B19 | D29: =Assumptions!B18-Assumptions!B19
A30: Equity Value ($M) | B30: =B28-B29 | C30: =C28-C29 | D30: =D28-D29
A31: Shares Outstanding (M) | B31: =Assumptions!B5 | C31: =Assumptions!B5 | D31: =Assumptions!B5
A32: Implied Price per Share ($) | B32: =B30/B31 | C32: =C30/C31 | D32: =D30/D31
A33: Current Price ($) | B33: =Assumptions!B4 | C33: =Assumptions!B4 | D33: =Assumptions!B4
A34: Upside / (Downside) | B34: =(B32-B33)/B33 | C34: =(C32-C33)/C33 | D34: =(D32-D33)/D33

Sheet Sensitivity
A1: Sensitivity Analysis
A3: Implied Price: WACC vs Terminal Growth Rate (Perpetuity)
A4: WACC \ TGR | B4: 0.02 | C4: 0.025 | D4: 0.03 | E4: 0.035 | F4: 0.04
A5: 0.07 | B5: =('FCF Projections'!C17/(1+$A5)^1+'FCF Projections'!D17/(1+$A5)^2+'FCF Projections'!E17/(1+$A5)^3+'FCF Projections'!F17/(1+$A5)^4+'FCF Projections'!G17/(1+$A5)^5+('FCF Projections'!G17*(1+B$4))/($A5-B$4)/(1+$A5)^5-(Assumptions!B18-Assumptions!B19))/Assumptions!B5 | C5: =('FCF Projections'!C17/(1+$A5)^1+'FCF Projections'!D17/(1+$A5)^2+'FCF Projections'!E17/(1+$A5)^3+'FCF Projections'!F17/(1+$A5)^4+'FCF Projections'!G17/(1+$A5)^5+('FCF Projections'!G17*(1+C$4))/($A5-C$4)/(1+$A5)^5-(Assumptions!B18-Assumptions!B19))/Assumptions!B5 | D5: =('FCF Projections'!C17/(1+$A5)^1+'FCF Projections'!D17/(1+$A5)^2+'FCF Projections'!E17/(1+$A5)^3+'FCF Projections'!F17/(1+$A5)^4+'FCF Projections'!G17/(1+$A5)^5+('FCF Projections'!G17*(1+D$4))/($A5-D$4)/(1+$A5)^5-(Assumptions!B18-Assumptions!B19))/Assumptions!B5 | E5: =('FCF Projections'!C17/(1+$A5)^1+'FCF Projections'!D17/(1+$A5)^2+'FCF Projections'!E17/(1+$A5)^3+'FCF Projections'!F17/(1+$A5)^4+'FCF Projections'!G17/(1+$A5)^5+('FCF Projections'!G17*(1+E$4))/($A5-E$4)/(1+$A5)^5-(Assumptions!B18-Assumptions!B19))/Assumptions!B5 | F5: =('FCF Projections'!C17/(1+$A5)^1+'FCF Projections'!D17/(1+$A5)^2+'FCF Projections'!E17/(1+$A5)^3+'FCF Projections'!F17/(1+$A5)^4+'FCF Projections'!G17/(1+$A5)^5+('FCF Projections'!G17*(1+F$4))/($A5-F$4)/(1+$A5)^5-(Assumptions!B18-Assumptions!B19))/Assumptions!B5
A6: 0.08 | B6: =('FCF Projections'!C17/(1+$A6)^1+'FCF Projections'!D17/(1+$A6)^2+'FCF Projections'!E17/(1+$A6)^3+'FCF Projections'!F17/(1+$A6)^4+'FCF Projections'!G17/(1+$A6)^5+('FCF Projections'!G17*(1+B$4))/($A6-B$4)/(1+$A6)^5-(Assumptions!B18-Assumptions!B19))/Assumptions!B5 | C6: =('FCF Projections'!C17/(1+$A6)^1+'FCF Projections'!D17/(1+$A6)^2+'FCF Projections'!E17/(1+$A6)^3+'FCF Projections'!F17/(1+$A6)^4+'FCF Projections'!G17/(1+$A6)^5+('FCF Projections'!G17*(1+C$4))/($A6-C$4)/(1+$A6)^5-(Assumptions!B18-Assumptions!B19))/Assumptions!B5 | D6: =('FCF Projections'!C17/(1+$A6)^1+'FCF Projections'!D17/(1+$A6)^2+'FCF Projections'!E17/(1+$A6)^3+'FCF Projections'!F17/(1+$A6)^4+'FCF Projections'!G17/(1+$A6)^5+('FCF Projections'!G17*(1+D$4))/($A6-D$4)/(1+$A6)^5-(Assumptions!B18-Assumptions!B19))/Assumptions!B5 | E6: =('FCF Projections'!C17/(1+$A6)^1+'FCF Projections'!D17/(1+$A6)^2+'FCF Projections'!E17/(1+$A6)^3+'FCF Projections'!F17/(1+$A6)^4+'FCF Projections'!G17/(1+$A6)^5+('FCF Projections'!G17*(1+E$4))/($A6-E$4)/(1+$A6)^5-(Assumptions!B18-Assumptions!B19))/Assumptions!B5 | F6: =('FCF Projections'!C17/(1+$A6)^1+'FCF Projections'!D17/(1+$A6)^2+'FCF Projections'!E17/(1+$A6)^3+'FCF Projections'!F17/(1+$A6)^4+'FCF Projections'!G17/(1+$A6)^5+('FCF Projections'!G17*(1+F$4))/($A6-F$4)/(1+$A6)^5-(Assumptions!B18-Assumptions!B19))/Assumptions!B5
A7: 0.09 | B7: =('FCF Projections'!C17/(1+$A7)^1+'FCF Projections'!D17/(1+$A7)^2+'FCF Projections'!E17/(1+$A7)^3+'FCF Projections'!F17/(1+$A7)^4+'FCF Projections'!G17/(1+$A7)^5+('FCF Projections'!G17*(1+B$4))/($A7-B$4)/(1+$A7)^5-(Assumptions!B18-Assumptions!B19))/Assumptions!B5 | C7: =('FCF Projections'!C17/(1+$A7)^1+'FCF Projections'!D17/(1+$A7)^2+'FCF Projections'!E17/(1+$A7)^3+'FCF Projections'!F17/(1+$A7)^4+'FCF Projections'!G17/(1+$A7)^5+('FCF Projections'!G17*(1+C$4))/($A7-C$4)/(1+$A7)^5-(Assumptions!B18-Assumptions!B19))/Assumptions!B5 | D7: =('FCF Projections'!C17/(1+$A7)^1+'FCF Projections'!D17/(1+$A7)^2+'FCF Projections'!E17/(1+$A7)^3+'FCF Projections'!F17/(1+$A7)^4+'FCF Projections'!G17/(1+$A7)^5+('FCF Projections'!G17*(1+D$4))/($A7-D$4)/(1+$A7)^5-(Assumptions!B18-Assumptions!B19))/Assumptions!B5 | E7: =('FCF Projections'!C17/(1+$A7)^1+'FCF Projections'!D17/(1+$A7)^2+'FCF Projections'!E17/(1+$A7)^3+'FCF Projections'!F17/(1+$A7)^4+'FCF Projections'!G17/(1+$A7)^5+('FCF Projections'!G17*(1+E$4))/($A7-E$4)/(1+$A7)^5-(Assumptions!B18-Assumptions!B19))/Assumptions!B5 | F7: =('FCF Projections'!C17/(1+$A7)^1+'FCF Projections'!D17/(1+$A7)^2+'FCF Projections'!E17/(1+$A7)^3+'FCF Projections'!F17/(1+$A7)^4+'FCF Projections'!G17/(1+$A7)^5+('FCF Projections'!G17*(1+F$4))/($A7-F$4)/(1+$A7)^5-(Assumptions!B18-Assumptions!B19))/Assumptions!B5
A8: 0.1 | B8: =('FCF Projections'!C17/(1+$A8)^1+'FCF Projections'!D17/(1+$A8)^2+'FCF Projections'!E17/(1+$A8)^3+'FCF Projections'!F17/(1+$A8)^4+'FCF Projections'!G17/(1+$A8)^5+('FCF Projections'!G17*(1+B$4))/($A8-B$4)/(1+$A8)^5-(Assumptions!B18-Assumptions!B19))/Assumptions!B5 | C8: =('FCF Projections'!C17/(1+$A8)^1+'FCF Projections'!D17/(1+$A8)^2+'FCF Projections'!E17/(1+$A8)^3+'FCF Projections'!F17/(1+$A8)^4+'FCF Projections'!G17/(1+$A8)^5+('FCF Projections'!G17*(1+C$4))/($A8-C$4)/(1+$A8)^5-(Assumptions!B18-Assumptions!B19))/Assumptions!B5 | D8: =('FCF Projections'!C17/(1+$A8)^1+'FCF Projections'!D17/(1+$A8)^2+'FCF Projections'!E17/(1+$A8)^3+'FCF Projections'!F17/(1+$A8)^4+'FCF Projections'!G17/(1+$A8)^5+('FCF Projections'!G17*(1+D$4))/($A8-D$4)/(1+$A8)^5-(Assumptions!B18-Assumptions!B19))/Assumptions!B5 | E8: =('FCF Projections'!C17/(1+$A8)^1+'FCF Projections'!D17/(1+$A8)^2+'FCF Projections'!E17/(1+$A8)^3+'FCF Projections'!F17/(1+$A8)^4+'FCF Projections'!G17/(1+$A8)^5+('FCF Projections'!G17*(1+E$4))/($A8-E$4)/(1+$A8)^5-(Assumptions!B18-Assumptions!B19))/Assumptions!B5 | F8: =('FCF Projections'!C17/(1+$A8)^1+'FCF Projections'!D17/(1+$A8)^2+'FCF Projections'!E17/(1+$A8)^3+'FCF Projections'!F17/(1+$A8)^4+'FCF Projections'!G17/(1+$A8)^5+('FCF Projections'!G17*(1+F$4))/($A8-F$4)/(1+$A8)^5-(Assumptions!B18-Assumptions!B19))/Assumptions!B5
A9: 0.11 | B9: =('FCF Projections'!C17/(1+$A9)^1+'FCF Projections'!D17/(1+$A9)^2+'FCF Projections'!E17/(1+$A9)^3+'FCF Projections'!F17/(1+$A9)^4+'FCF Projections'!G17/(1+$A9)^5+('FCF Projections'!G17*(1+B$4))/($A9-B$4)/(1+$A9)^5-(Assumptions!B18-Assumptions!B19))/Assumptions!B5 | C9: =('FCF Projections'!C17/(1+$A9)^1+'FCF Projections'!D17/(1+$A9)^2+'FCF Projections'!E17/(1+$A9)^3+'FCF Projections'!F17/(1+$A9)^4+'FCF Projections'!G17/(1+$A9)^5+('FCF Projections'!G17*(1+C$4))/($A9-C$4)/(1+$A9)^5-(Assumptions!B18-Assumptions!B19))/Assumptions!B5 | D9: =('FCF Projections'!C17/(1+$A9)^1+'FCF Projections'!D17/(1+$A9)^2+'FCF Projections'!E17/(1+$A9)^3+'FCF Projections'!F17/(1+$A9)^4+'FCF Projections'!G17/(1+$A9)^5+('FCF Projections'!G17*(1+D$4))/($A9-D$4)/(1+$A9)^5-(Assumptions!B18-Assumptions!B19))/Assumptions!B5 | E9: =('FCF Projections'!C17/(1+$A9)^1+'FCF Projections'!D17/(1+$A9)^2+'FCF Projections'!E17/(1+$A9)^3+'FCF Projections'!F17/(1+$A9)^4+'FCF Projections'!G17/(1+$A9)^5+('FCF Projections'!G17*(1+E$4))/($A9-E$4)/(1+$A9)^5-(Assumptions!B18-Assumptions!B19))/Assumptions!B5 | F9: =('FCF Projections'!C17/(1+$A9)^1+'FCF Projections'!D17/(1+$A9)^2+'FCF Projections'!E17/(1+$A9)^3+'FCF Projections'!F17/(1+$A9)^4+'FCF Projections'!G17/(1+$A9)^5+('FCF Projections'!G17*(1+F$4))/($A9-F$4)/(1+$A9)^5-(Assumptions!B18-Assumptions!B19))/Assumptions!B5
A10: 0.12 | B10: =('FCF Projections'!C17/(1+$A10)^1+'FCF Projections'!D17/(1+$A10)^2+'FCF Projections'!E17/(1+$A10)^3+'FCF Projections'!F17/(1+$A10)^4+'FCF Projections'!G17/(1+$A10)^5+('FCF Projections'!G17*(1+B$4))/($A10-B$4)/(1+$A10)^5-(Assumptions!B18-Assumptions!B19))/Assumptions!B5 | C10: =('FCF Projections'!C17/(1+$A10)^1+'FCF Projections'!D17/(1+$A10)^2+'FCF Projections'!E17/(1+$A10)^3+'FCF Projections'!F17/(1+$A10)^4+'FCF Projections'!G17/(1+$A10)^5+('FCF Projections'!G17*(1+C$4))/($A10-C$4)/(1+$A10)^5-(Assumptions!B18-Assumptions!B19))/Assumptions!B5 | D10: =('FCF Projections'!C17/(1+$A10)^1+'FCF Projections'!D17/(1+$A10)^2+'FCF Projections'!E17/(1+$A10)^3+'FCF Projections'!F17/(1+$A10)^4+'FCF Projections'!G17/(1+$A10)^5+('FCF Projections'!G17*(1+D$4))/($A10-D$4)/(1+$A10)^5-(Assumptions!B18-Assumptions!B19))/Assumptions!B5 | E10: =('FCF Projections'!C17/(1+$A10)^1+'FCF Projections'!D17/(1+$A10)^2+'FCF Projections'!E17/(1+$A10)^3+'FCF Projections'!F17/(1+$A10)^4+'FCF Projections'!G17/(1+$A10)^5+('FCF Projections'!G17*(1+E$4))/($A10-E$4)/(1+$A10)^5-(Assumptions!B18-Assumptions!B19))/Assumptions!B5 | F10: =('FCF Projections'!C17/(1+$A10)^1+'FCF Projections'!D17/(1+$A10)^2+'FCF Projections'!E17/(1+$A10)^3+'FCF Projections'!F17/(1+$A10)^4+'FCF Projections'!G17/(1+$A10)^5+('FCF Projections'!G17*(1+F$4))/($A10-F$4)/(1+$A10)^5-(Assumptions!B18-Assumptions!B19))/Assumptions!B5
A13: Implied Price: WACC vs Exit EV/EBITDA Multiple
A14: WACC \ Exit Mult | B14: 16 | C14: 18 | D14: 20 | E14: 22 | F14: 24
A15: 0.07 | B15: =('FCF Projections'!C17/(1+$A15)^1+'FCF Projections'!D17/(1+$A15)^2+'FCF Projections'!E17/(1+$A15)^3+'FCF Projections'!F17/(1+$A15)^4+'FCF Projections'!G17/(1+$A15)^5+('FCF Projections'!G7*B$14)/(1+$A15)^5-(Assumptions!B18-Assumptions!B19))/Assumptions!B5 | C15: =('FCF Projections'!C17/(1+$A15)^1+'FCF Projections'!D17/(1+$A15)^2+'FCF Projections'!E17/(1+$A15)^3+'FCF Projections'!F17/(1+$A15)^4+'FCF Projections'!G17/(1+$A15)^5+('FCF Projections'!G7*C$14)/(1+$A15)^5-(Assumptions!B18-Assumptions!B19))/Assumptions!B5 | D15: =('FCF Projections'!C17/(1+$A15)^1+'FCF Projections'!D17/(1+$A15)^2+'FCF Projections'!E17/(1+$A15)^3+'FCF Projections'!F17/(1+$A15)^4+'FCF Projections'!G17/(1+$A15)^5+('FCF Projections'!G7*D$14)/(1+$A15)^5-(Assumptions!B18-Assumptions!B19))/Assumptions!B5 | E15: =('FCF Projections'!C17/(1+$A15)^1+'FCF Projections'!D17/(1+$A15)^2+'FCF Projections'!E17/(1+$A15)^3+'FCF Projections'!F17/(1+$A15)^4+'FCF Projections'!G17/(1+$A15)^5+('FCF Projections'!G7*E$14)/(1+$A15)^5-(Assumptions!B18-Assumptions!B19))/Assumptions!B5 | F15: =('FCF Projections'!C17/(1+$A15)^1+'FCF Projections'!D17/(1+$A15)^2+'FCF Projections'!E17/(1+$A15)^3+'FCF Projections'!F17/(1+$A15)^4+'FCF Projections'!G17/(1+$A15)^5+('FCF Projections'!G7*F$14)/(1+$A15)^5-(Assumptions!B18-Assumptions!B19))/Assumptions!B5
A16: 0.08 | B16: =('FCF Projections'!C17/(1+$A16)^1+'FCF Projections'!D17/(1+$A16)^2+'FCF Projections'!E17/(1+$A16)^3+'FCF Projections'!F17/(1+$A16)^4+'FCF Projections'!G17/(1+$A16)^5+('FCF Projections'!G7*B$14)/(1+$A16)^5-(Assumptions!B18-Assumptions!B19))/Assumptions!B5 | C16: =('FCF Projections'!C17/(1+$A16)^1+'FCF Projections'!D17/(1+$A16)^2+'FCF Projections'!E17/(1+$A16)^3+'FCF Projections'!F17/(1+$A16)^4+'FCF Projections'!G17/(1+$A16)^5+('FCF Projections'!G7*C$14)/(1+$A16)^5-(Assumptions!B18-Assumptions!B19))/Assumptions!B5 | D16: =('FCF Projections'!C17/(1+$A16)^1+'FCF Projections'!D17/(1+$A16)^2+'FCF Projections'!E17/(1+$A16)^3+'FCF Projections'!F17/(1+$A16)^4+'FCF Projections'!G17/(1+$A16)^5+('FCF Projections'!G7*D$14)/(1+$A16)^5-(Assumptions!B18-Assumptions!B19))/Assumptions!B5 | E16: =('FCF Projections'!C17/(1+$A16)^1+'FCF Projections'!D17/(1+$A16)^2+'FCF Projections'!E17/(1+$A16)^3+'FCF Projections'!F17/(1+$A16)^4+'FCF Projections'!G17/(1+$A16)^5+('FCF Projections'!G7*E$14)/(1+$A16)^5-(Assumptions!B18-Assumptions!B19))/Assumptions!B5 | F16: =('FCF Projections'!C17/(1+$A16)^1+'FCF Projections'!D17/(1+$A16)^2+'FCF Projections'!E17/(1+$A16)^3+'FCF Projections'!F17/(1+$A16)^4+'FCF Projections'!G17/(1+$A16)^5+('FCF Projections'!G7*F$14)/(1+$A16)^5-(Assumptions!B18-Assumptions!B19))/Assumptions!B5
A17: 0.09 | B17: =('FCF Projections'!C17/(1+$A17)^1+'FCF Projections'!D17/(1+$A17)^2+'FCF Projections'!E17/(1+$A17)^3+'FCF Projections'!F17/(1+$A17)^4+'FCF Projections'!G17/(1+$A17)^5+('FCF Projections'!G7*B$14)/(1+$A17)^5-(Assumptions!B18-Assumptions!B19))/Assumptions!B5 | C17: =('FCF Projections'!C17/(1+$A17)^1+'FCF Projections'!D17/(1+$A17)^2+'FCF Projections'!E17/(1+$A17)^3+'FCF Projections'!F17/(1+$A17)^4+'FCF Projections'!G17/(1+$A17)^5+('FCF Projections'!G7*C$14)/(1+$A17)^5-(Assumptions!B18-Assumptions!B19))/Assumptions!B5 | D17: =('FCF Projections'!C17/(1+$A17)^1+'FCF Projections'!D17/(1+$A17)^2+'FCF Projections'!E17/(1+$A17)^3+'FCF Projections'!F17/(1+$A17)^4+'FCF Projections'!G17/(1+$A17)^5+('FCF Projections'!G7*D$14)/(1+$A17)^5-(Assumptions!B18-Assumptions!B19))/Assumptions!B5 | E17: =('FCF Projections'!C17/(1+$A17)^1+'FCF Projections'!D17/(1+$A17)^2+'FCF Projections'!E17/(1+$A17)^3+'FCF Projections'!F17/(1+$A17)^4+'FCF Projections'!G17/(1+$A17)^5+('FCF Projections'!G7*E$14)/(1+$A17)^5-(Assumptions!B18-Assumptions!B19))/Assumptions!B5 | F17: =('FCF Projections'!C17/(1+$A17)^1+'FCF Projections'!D17/(1+$A17)^2+'FCF Projections'!E17/(1+$A17)^3+'FCF Projections'!F17/(1+$A17)^4+'FCF Projections'!G17/(1+$A17)^5+('FCF Projections'!G7*F$14)/(1+$A17)^5-(Assumptions!B18-Assumptions!B19))/Assumptions!B5
A18: 0.1 | B18: =('FCF Projections'!C17/(1+$A18)^1+'FCF Projections'!D17/(1+$A18)^2+'FCF Projections'!E17/(1+$A18)^3+'FCF Projections'!F17/(1+$A18)^4+'FCF Projections'!G17/(1+$A18)^5+('FCF Projections'!G7*B$14)/(1+$A18)^5-(Assumptions!B18-Assumptions!B19))/Assumptions!B5 | C18: =('FCF Projections'!C17/(1+$A18)^1+'FCF Projections'!D17/(1+$A18)^2+'FCF Projections'!E17/(1+$A18)^3+'FCF Projections'!F17/(1+$A18)^4+'FCF Projections'!G17/(1+$A18)^5+('FCF Projections'!G7*C$14)/(1+$A18)^5-(Assumptions!B18-Assumptions!B19))/Assumptions!B5 | D18: =('FCF Projections'!C17/(1+$A18)^1+'FCF Projections'!D17/(1+$A18)^2+'FCF Projections'!E17/(1+$A18)^3+'FCF Projections'!F17/(1+$A18)^4+'FCF Projections'!G17/(1+$A18)^5+('FCF Projections'!G7*D$14)/(1+$A18)^5-(Assumptions!B18-Assumptions!B19))/Assumptions!B5 | E18: =('FCF Projections'!C17/(1+$A18)^1+'FCF Projections'!D17/(1+$A18)^2+'FCF Projections'!E17/(1+$A18)^3+'FCF Projections'!F17/(1+$A18)^4+'FCF Projections'!G17/(1+$A18)^5+('FCF Projections'!G7*E$14)/(1+$A18)^5-(Assumptions!B18-Assumptions!B19))/Assumptions!B5 | F18: =('FCF Projections'!C17/(1+$A18)^1+'FCF Projections'!D17/(1+$A18)^2+'FCF Projections'!E17/(1+$A18)^3+'FCF Projections'!F17/(1+$A18)^4+'FCF Projections'!G17/(1+$A18)^5+('FCF Projections'!G7*F$14)/(1+$A18)^5-(Assumptions!B18-Assumptions!B19))/Assumptions!B5
A19: 0.11 | B19: =('FCF Projections'!C17/(1+$A19)^1+'FCF Projections'!D17/(1+$A19)^2+'FCF Projections'!E17/(1+$A19)^3+'FCF Projections'!F17/(1+$A19)^4+'FCF Projections'!G17/(1+$A19)^5+('FCF Projections'!G7*B$14)/(1+$A19)^5-(Assumptions!B18-Assumptions!B19))/Assumptions!B5 | C19: =('FCF Projections'!C17/(1+$A19)^1+'FCF Projections'!D17/(1+$A19)^2+'FCF Projections'!E17/(1+$A19)^3+'FCF Projections'!F17/(1+$A19)^4+'FCF Projections'!G17/(1+$A19)^5+('FCF Projections'!G7*C$14)/(1+$A19)^5-(Assumptions!B18-Assumptions!B19))/Assumptions!B5 | D19: =('FCF Projections'!C17/(1+$A19)^1+'FCF Projections'!D17/(1+$A19)^2+'FCF Projections'!E17/(1+$A19)^3+'FCF Projections'!F17/(1+$A19)^4+'FCF Projections'!G17/(1+$A19)^5+('FCF Projections'!G7*D$14)/(1+$A19)^5-(Assumptions!B18-Assumptions!B19))/Assumptions!B5 | E19: =('FCF Projections'!C17/(1+$A19)^1+'FCF Projections'!D17/(1+$A19)^2+'FCF Projections'!E17/(1+$A19)^3+'FCF Projections'!F17/(1+$A19)^4+'FCF Projections'!G17/(1+$A19)^5+('FCF Projections'!G7*E$14)/(1+$A19)^5-(Assumptions!B18-Assumptions!B19))/Assumptions!B5 | F19: =('FCF Projections'!C17/(1+$A19)^1+'FCF Projections'!D17/(1+$A19)^2+'FCF Projections'!E17/(1+$A19)^3+'FCF Projections'!F17/(1+$A19)^4+'FCF Projections'!G17/(1+$A19)^5+('FCF Projections'!G7*F$14)/(1+$A19)^5-(Assumptions!B18-Assumptions!B19))/Assumptions!B5
A20: 0.12 | B20: =('FCF Projections'!C17/(1+$A20)^1+'FCF Projections'!D17/(1+$A20)^2+'FCF Projections'!E17/(1+$A20)^3+'FCF Projections'!F17/(1+$A20)^4+'FCF Projections'!G17/(1+$A20)^5+('FCF Projections'!G7*B$14)/(1+$A20)^5-(Assumptions!B18-Assumptions!B19))/Assumptions!B5 | C20: =('FCF Projections'!C17/(1+$A20)^1+'FCF Projections'!D17/(1+$A20)^2+'FCF Projections'!E17/(1+$A20)^3+'FCF Projections'!F17/(1+$A20)^4+'FCF Projections'!G17/(1+$A20)^5+('FCF Projections'!G7*C$14)/(1+$A20)^5-(Assumptions!B18-Assumptions!B19))/Assumptions!B5 | D20: =('FCF Projections'!C17/(1+$A20)^1+'FCF Projections'!D17/(1+$A20)^2+'FCF Projections'!E17/(1+$A20)^3+'FCF Projections'!F17/(1+$A20)^4+'FCF Projections'!G17/(1+$A20)^5+('FCF Projections'!G7*D$14)/(1+$A20)^5-(Assumptions!B18-Assumptions!B19))/Assumptions!B5 | E20: =('FCF Projections'!C17/(1+$A20)^1+'FCF Projections'!D17/(1+$A20)^2+'FCF Projections'!E17/(1+$A20)^3+'FCF Projections'!F17/(1+$A20)^4+'FCF Projections'!G17/(1+$A20)^5+('FCF Projections'!G7*E$14)/(1+$A20)^5-(Assumptions!B18-Assumptions!B19))/Assumptions!B5 | F20: =('FCF Projections'!C17/(1+$A20)^1+'FCF Projections'!D17/(1+$A20)^2+'FCF Projections'!E17/(1+$A20)^3+'FCF Projections'!F17/(1+$A20)^4+'FCF Projections'!G17/(1+$A20)^5+('FCF Projections'!G7*F$14)/(1+$A20)^5-(Assumptions!B18-Assumptions!B19))/Assumptions!B5

Sheet Scenarios
A1: Scenario Analysis
A3: Assumption | B3: Bear Case | C3: Base Case | D3: Bull Case
A4: Revenue CAGR (5Y) | B4: 10% | C4: 13% | D4: 16%
A5: Terminal EBITDA Margin | B5: 18% | C5: 22% | D5: 26%
A6: WACC | B6: 11.0% | C6: 9.2% | D6: 8.0%
A7: Terminal Growth Rate | B7: 2.0% | C7: 3.0% | D7: 4.0%
A8: Exit EV/EBITDA | B8: 16.0x | C8: 20.0x | D8: 24.0x
A10: Implied Price/Share | B10: 50 | C10: =Valuation!D32 | D10: 140
A11: Upside / (Downside) | B11: =(B10-Assumptions!B4)/Assumptions!B4 | C11: =(C10-Assumptions!B4)/Assumptions!B4 | D11: =(D10-Assumptions!B4)/Assumptions!B4
