Workbook

Sheet Assumptions
A1: Key Assumptions � MELI (MercadoLibre) [UPDATED POST Q4-2025]
B3: 2022A | C3: 2023A | D3: 2024A | E3: 2025A | F3: 2026E | G3: 2027E | H3: 2028E | I3: 2029E
A4: Revenue Growth % | B4: 0.397 | C4: 0.374 | D4: 0.436 | E4: 0.39 | F4: 0.25 | G4: 0.2 | H4: 0.18 | I4: 0.15
A5: COGS % of Revenue | B5: 0.522 | C5: 0.518 | D5: 0.539 | E5: 0.546 | F5: 0.54 | G5: 0.531 | H5: 0.52 | I5: 0.515
A6: S&M % of Revenue | B6: 0.12 | C6: 0.115 | D6: 0.11 | E6: 0.112 | F6: 0.108 | G6: 0.1 | H6: 0.095 | I6: 0.09
A7: Tech & Product Dev % Rev | B7: 0.095 | C7: 0.09 | D7: 0.088 | E7: 0.092 | F7: 0.088 | G7: 0.085 | H7: 0.082 | I7: 0.08
A8: G&A % of Revenue | B8: 0.06 | C8: 0.055 | D8: 0.052 | E8: 0.053 | F8: 0.05 | G8: 0.048 | H8: 0.046 | I8: 0.044
A9: Provision for Doubtful % Rev | B9: 0.045 | C9: 0.042 | D9: 0.04 | E9: 0.042 | F9: 0.038 | G9: 0.035 | H9: 0.032 | I9: 0.03
A10: D&A % of Revenue | B10: 0.03 | C10: 0.03 | D10: 0.028 | E10: 0.028 | F10: 0.028 | G10: 0.028 | H10: 0.028 | I10: 0.028
A11: Tax Rate | B11: 0.3 | C11: 0.28 | D11: 0.27 | E11: 0.285 | F11: 0.275 | G11: 0.27 | H11: 0.27 | I11: 0.27
A13: Capex % of Revenue | B13: 0.048 | C13: 0.059 | D13: 0.059 | E13: 0.043 | F13: 0.039 | G13: 0.036 | H13: 0.033 | I13: 0.031
A14: AR Days | B14: 45 | C14: 42 | D14: 40 | E14: 38 | F14: 37 | G14: 36 | H14: 35 | I14: 34
A15: Inventory Days | B15: 15 | C15: 14 | D15: 13 | E15: 12 | F15: 12 | G15: 12 | H15: 11 | I15: 11
A16: AP Days | B16: 60 | C16: 58 | D16: 55 | E16: 53 | F16: 52 | G16: 51 | H16: 50 | I16: 49
... A20: Shares Outstanding (M) | B20: 50.2 | C20: 50.4 | D20: 50.7 | E20: 51 | F20: 51 | G20: 51 | H20: 51 | I20: 51

Sheet Income Statement
A1: Income Statement � MELI ($M) [UPDATED POST Q4-2025]
B3: 2022A | C3: 2023A | D3: 2024A | E3: 2025A | F3: 2026E | G3: 2027E | H3: 2028E | I3: 2029E
A4: Revenue | B4: 10537 | C4: 14473 | D4: 20777 | E4: 28900 | F4: =E4*(1+Assumptions!F4) | G4: =F4*(1+Assumptions!G4) | H4: =G4*(1+Assumptions!H4) | I4: =H4*(1+Assumptions!I4)
A5: YoY Growth % | B5: 0.397 | C5: =(C4-B4)/B4 | D5: =(D4-C4)/C4 | E5: =(E4-D4)/D4 | F5: =Assumptions!F4 | G5: =Assumptions!G4 | H5: =Assumptions!H4 | I5: =Assumptions!I4
A6: (-) Cost of Revenue | B6: 5500 | C6: 7500 | D6: 11200 | E6: 15780 | F6: =F4*Assumptions!F5 | G6: =G4*Assumptions!G5 | H6: =H4*Assumptions!H5 | I6: =I4*Assumptions!I5
A7: Gross Profit | B7: =B4-B6 | C7: =C4-C6 | D7: =D4-D6 | E7: =E4-E6 | F7: =F4-F6 | G7: =G4-G6 | H7: =H4-H6 | I7: =I4-I6
A8: Gross Margin % | B8: =B7/B4 | C8: =C7/C4 | D8: =D7/D4 | E8: =E7/E4 | F8: =F7/F4 | G8: =G7/G4 | H8: =H7/H4 | I8: =I7/I4
A10: (-) Sales & Marketing | B10: 1264 | C10: 1664 | D10: 2286 | E10: 3237 | F10: =F4*Assumptions!F6 | G10: =G4*Assumptions!G6 | H10: =H4*Assumptions!H6 | I10: =I4*Assumptions!I6
A11: (-) Technology & Product Dev | B11: 1001 | C11: 1302 | D11: 1828 | E11: 2659 | F11: =F4*Assumptions!F7 | G11: =G4*Assumptions!G7 | H11: =H4*Assumptions!H7 | I11: =I4*Assumptions!I7
A12: (-) General & Administrative | B12: 632 | C12: 796 | D12: 1080 | E12: 1532 | F12: =F4*Assumptions!F8 | G12: =G4*Assumptions!G8 | H12: =H4*Assumptions!H8 | I12: =I4*Assumptions!I8
A13: (-) Provision for Doubtful Accts | B13: 474 | C13: 608 | D13: 831 | E13: 1214 | F13: =F4*Assumptions!F9 | G13: =G4*Assumptions!G9 | H13: =H4*Assumptions!H9 | I13: =I4*Assumptions!I9
A14: Total Operating Expenses | B14: =B10+B11+B12+B13 | C14: =C10+C11+C12+C13 | D14: =D10+D11+D12+D13 | E14: =E10+E11+E12+E13 | F14: =F10+F11+F12+F13 | G14: =G10+G11+G12+G13 | H14: =H10+H11+H12+H13 | I14: =I10+I11+I12+I13
A16: Operating Income (EBIT) | B16: =B7-B14 | C16: =C7-C14 | D16: =D7-D14 | E16: =E7-E14 | F16: =F7-F14 | G16: =G7-G14 | H16: =H7-H14 | I16: =I7-I14
A17: Operating Margin % | B17: =B16/B4 | C17: =C16/C4 | D17: =D16/D4 | E17: =E16/E4 | F17: =F16/F4 | G17: =G16/G4 | H17: =H16/H4 | I17: =I16/I4
A19: (-) Interest Expense | B19: 58 | C19: 247 | D19: 608 | E19: 780 | F19: ='Balance Sheet'!F14*Assumptions!F19 | G19: ='Balance Sheet'!G14*Assumptions!G19 | H19: ='Balance Sheet'!H14*Assumptions!H19 | I19: ='Balance Sheet'!I14*Assumptions!I19
A20: (+) Other Income / (Expense) | B20: 120 | C20: 180 | D20: 250 | E20: 320 | F20: 250 | G20: 250 | H20: 250 | I20: 250
A21: Pre-Tax Income | B21: =B16-B19+B20 | C21: =C16-C19+C20 | D21: =D16-D19+D20 | E21: =E16-E19+E20 | F21: =F16-F19+F20 | G21: =G16-G19+G20 | H21: =H16-H19+H20 | I21: =I16-I19+I20
A22: (-) Income Tax | B22: =B21*Assumptions!B11 | C22: =C21*Assumptions!C11 | D22: =D21*Assumptions!D11 | E22: =E21*Assumptions!E11 | F22: =F21*Assumptions!F11 | G22: =G21*Assumptions!G11 | H22: =H21*Assumptions!H11 | I22: =I21*Assumptions!I11
A23: Effective Tax Rate | B23: =IF(B21=0,0,B22/B21) | C23: =IF(C21=0,0,C22/C21) | D23: =IF(D21=0,0,D22/D21) | E23: =IF(E21=0,0,E22/E21) | F23: =IF(F21=0,0,F22/F21) | G23: =IF(G21=0,0,G22/G21) | H23: =IF(H21=0,0,H22/H21) | I23: =IF(I21=0,0,I22/I21)
A24: Net Income | B24: =B21-B22 | C24: =C21-C22 | D24: =D21-D22 | E24: =E21-E22 | F24: =F21-F22 | G24: =G21-G22 | H24: =H21-H22 | I24: =I21-I22
A25: Net Margin % | B25: =B24/B4 | C25: =C24/C4 | D25: =D24/D4 | E25: =E24/E4 | F25: =F24/F4 | G25: =G24/G4 | H25: =H24/H4 | I25: =I24/I4
A27: EPS (Diluted) | B27: =B24/Assumptions!B20 | C27: =C24/Assumptions!C20 | D27: =D24/Assumptions!D20 | E27: =E24/Assumptions!E20 | F27: =F24/Assumptions!F20 | G27: =G24/Assumptions!G20 | H27: =H24/Assumptions!H20 | I27: =I24/Assumptions!I20
A28: EBITDA | B28: =B16+B4*Assumptions!B10 | C28: =C16+C4*Assumptions!C10 | D28: =D16+D4*Assumptions!D10 | E28: =E16+E4*Assumptions!E10 | F28: =F16+F4*Assumptions!F10 | G28: =G16+G4*Assumptions!G10 | H28: =H16+H4*Assumptions!H10 | I28: =I16+I4*Assumptions!I10
A29: EBITDA Margin % | B29: =B28/B4 | C29: =C28/C4 | D29: =D28/D4 | E29: =E28/E4 | F29: =F28/F4 | G29: =G28/G4 | H29: =H28/H4 | I29: =I28/I4

Sheet Balance Sheet
A1: Balance Sheet � MELI ($M) [UPDATED POST Q4-2025]
B3: 2022A | C3: 2023A | D3: 2024A | E3: 2025A | F3: 2026E | G3: 2027E | H3: 2028E | I3: 2029E
A4: ASSETS
A5: Cash & Equivalents | B5: 1550 | C5: 2100 | D5: 2600 | E5: 3200 | F5: =E5+'Cash Flow'!F21 | G5: =F5+'Cash Flow'!G21 | H5: =G5+'Cash Flow'!H21 | I5: =H5+'Cash Flow'!I21
A6: Short-Term Investments | B6: 2200 | C6: 2800 | D6: 4500 | E6: 5400 | F6: =E6*1.12 | G6: =F6*1.12 | H6: =G6*1.12 | I6: =H6*1.12
A7: Accounts Receivable | B7: 1300 | C7: 1665 | D7: 2277 | E7: 3010 | F7: ='Income Statement'!F4*Assumptions!F14/365 | G7: ='Income Statement'!G4*Assumptions!G14/365 | H7: ='Income Statement'!H4*Assumptions!H14/365 | I7: ='Income Statement'!I4*Assumptions!I14/365
A8: Inventory | B8: 433 | C8: 555 | D8: 740 | E8: 920 | F8: ='Income Statement'!F6*Assumptions!F15/365 | G8: ='Income Statement'!G6*Assumptions!G15/365 | H8: ='Income Statement'!H6*Assumptions!H15/365 | I8: ='Income Statement'!I6*Assumptions!I15/365
A9: Other Current Assets | B9: 800 | C9: 1000 | D9: 1400 | E9: 1800 | F9: =E9*1.08 | G9: =F9*1.08 | H9: =G9*1.08 | I9: =H9*1.08
A10: Total Current Assets | B10: =SUM(B5:B9) | C10: =SUM(C5:C9) | D10: =SUM(D5:D9) | E10: =SUM(E5:E9) | F10: =SUM(F5:F9) | G10: =SUM(G5:G9) | H10: =SUM(H5:H9) | I10: =SUM(I5:I9)
A12: PP&E (net) | B12: 1500 | C12: 2000 | D12: 3000 | E12: 3430 | F12: =E12+'Income Statement'!F4*Assumptions!F13-'Income Statement'!F4*Assumptions!F10 | G12: =F12+'Income Statement'!G4*Assumptions!G13-'Income Statement'!G4*Assumptions!G10 | H12: =G12+'Income Statement'!H4*Assumptions!H13-'Income Statement'!H4*Assumptions!H10 | I12: =H12+'Income Statement'!I4*Assumptions!I13-'Income Statement'!I4*Assumptions!I10
A13: Intangibles & Goodwill | B13: 350 | C13: 380 | D13: 420 | E13: 450 | F13: =E13 | G13: =F13 | H13: =G13 | I13: =H13
A14: Long-Term Debt Receivables | B14: 4000 | C14: 5200 | D14: 7200 | E14: 12500 | F14: =E14*1.18 | G14: =F14*1.18 | H14: =G14*1.18 | I14: =H14*1.18
A15: Other Non-Current Assets | B15: 1603 | C15: 1912 | D15: 3059 | E15: 3500 | F15: =E15*1.06 | G15: =F15*1.06 | H15: =G15*1.06 | I15: =H15*1.06
A16: Total Assets | B16: =B10+B12+B13+B14+B15 | C16: =C10+C12+C13+C14+C15 | D16: =D10+D12+D13+D14+D15 | E16: =E10+E12+E13+E14+E15 | F16: =F10+F12+F13+F14+F15 | G16: =G10+G12+G13+G14+G15 | H16: =H10+H12+H13+H14+H15 | I16: =I10+I12+I13+I14+I15
A18: LIABILITIES
A19: Accounts Payable | B19: 1733 | C19: 2299 | D19: 3130 | E19: 4200 | F19: ='Income Statement'!F6*Assumptions!F16/365 | G19: ='Income Statement'!G6*Assumptions!G16/365 | H19: ='Income Statement'!H6*Assumptions!H16/365 | I19: ='Income Statement'!I6*Assumptions!I16/365
A20: Accrued Liabilities | B20: 843 | C20: 1158 | D20: 1558 | E20: 2110 | F20: ='Income Statement'!F4*Assumptions!F17 | G20: ='Income Statement'!G4*Assumptions!G17 | H20: ='Income Statement'!H4*Assumptions!H17 | I20: ='Income Statement'!I4*Assumptions!I17
A21: Short-Term Debt | B21: 2500 | C21: 3200 | D21: 4500 | E21: 5200 | F21: =E21*1.08 | G21: =F21*1.08 | H21: =G21*1.08 | I21: =H21*1.08
A22: Other Current Liabilities | B22: 1200 | C22: 1500 | D22: 2000 | E22: 2400 | F22: =E22*1.06 | G22: =F22*1.06 | H22: =G22*1.06 | I22: =H22*1.06
A23: Total Current Liabilities | B23: =SUM(B19:B22) | C23: =SUM(C19:C22) | D23: =SUM(D19:D22) | E23: =SUM(E19:E22) | F23: =SUM(F19:F22) | G23: =SUM(G19:G22) | H23: =SUM(H19:H22) | I23: =SUM(I19:I22)
A25: Long-Term Debt | B25: 4500 | C25: 5200 | D25: 7200 | E25: 7800 | F25: =E25*1.03 | G25: =F25*1.03 | H25: =G25*1.03 | I25: =H25*1.03
A26: Other Non-Current Liabilities | B26: 1133 | C26: 1184 | D26: 2457 | E26: 2700 | F26: =E26*1.03 | G26: =F26*1.03 | H26: =G26*1.03 | I26: =H26*1.03
A27: Total Liabilities | B27: =B23+B25+B26 | C27: =C23+C25+C26 | D27: =D23+D25+D26 | E27: =E23+E25+E26 | F27: =F23+F25+F26 | G27: =G23+G25+G26 | H27: =H23+H25+H26 | I27: =I23+I25+I26
A29: EQUITY
A30: Retained Earnings | B30: =B16-B27-B31 | C30: =C16-C27-C31 | D30: =D16-D27-D31 | E30: =E16-E27-E31 | F30: =E30+'Income Statement'!F24 | G30: =F30+'Income Statement'!G24 | H30: =G30+'Income Statement'!H24 | I30: =H30+'Income Statement'!I24
A31: Other Equity | B31: 1827 | C31: 3071 | D31: 4351 | E31: 4351 | F31: =E31 | G31: =F31 | H31: =G31 | I31: =H31
A32: Total Equity | B32: =B30+B31 | C32: =C30+C31 | D32: =D30+D31 | E32: =E30+E31 | F32: =F30+F31 | G32: =G30+G31 | H32: =H30+H31 | I32: =I30+I31
A33: Total Liab. + Equity | B33: =B27+B32 | C33: =C27+C32 | D33: =D27+D32 | E33: =E27+E32 | F33: =F27+F32 | G33: =G27+G32 | H33: =H27+H32 | I33: =I27+I32
A34: Balance Check (should be 0) | B34: =B16-B33 | C34: =C16-C33 | D34: =D16-D33 | E34: =E16-E33 | F34: =F16-F33 | G34: =G16-G33 | H34: =H16-H33 | I34: =I16-I33

Sheet Cash Flow
A1: Cash Flow Statement � MELI ($M) [UPDATED POST Q4-2025]
B3: 2022A | C3: 2023A | D3: 2024A | E3: 2025A | F3: 2026E | G3: 2027E | H3: 2028E | I3: 2029E
A4: OPERATING ACTIVITIES
A5: Net Income | B5: ='Income Statement'!B24 | C5: ='Income Statement'!C24 | D5: ='Income Statement'!D24 | E5: ='Income Statement'!E24 | F5: ='Income Statement'!F24 | G5: ='Income Statement'!G24 | H5: ='Income Statement'!H24 | I5: ='Income Statement'!I24
A6: (+) Depreciation & Amortization | B6: ='Income Statement'!B4*Assumptions!B10 | C6: ='Income Statement'!C4*Assumptions!C10 | D6: ='Income Statement'!D4*Assumptions!D10 | E6: ='Income Statement'!E4*Assumptions!E10 | F6: ='Income Statement'!F4*Assumptions!F10 | G6: ='Income Statement'!G4*Assumptions!G10 | H6: ='Income Statement'!H4*Assumptions!H10 | I6: ='Income Statement'!I4*Assumptions!I10
A7: Changes in Working Capital | F7: =F8+F9+F10+F11+F12 | G7: =G8+G9+G10+G11+G12 | H7: =H8+H9+H10+H11+H12 | I7: =I8+I9+I10+I11+I12
A8: Change in AR | F8: =-('Balance Sheet'!F7-'Balance Sheet'!E7) | G8: =-('Balance Sheet'!G7-'Balance Sheet'!F7) | H8: =-('Balance Sheet'!H7-'Balance Sheet'!G7) | I8: =-('Balance Sheet'!I7-'Balance Sheet'!H7)
A9: Change in Inventory | F9: =-('Balance Sheet'!F8-'Balance Sheet'!E8) | G9: =-('Balance Sheet'!G8-'Balance Sheet'!F8) | H9: =-('Balance Sheet'!H8-'Balance Sheet'!G8) | I9: =-('Balance Sheet'!I8-'Balance Sheet'!H8)
A10: Change in AP | F10: ='Balance Sheet'!F19-'Balance Sheet'!E19 | G10: ='Balance Sheet'!G19-'Balance Sheet'!F19 | H10: ='Balance Sheet'!H19-'Balance Sheet'!G19 | I10: ='Balance Sheet'!I19-'Balance Sheet'!H19
A11: Change in Accrued Liab | F11: ='Balance Sheet'!F20-'Balance Sheet'!E20 | G11: ='Balance Sheet'!G20-'Balance Sheet'!F20 | H11: ='Balance Sheet'!H20-'Balance Sheet'!G20 | I11: ='Balance Sheet'!I20-'Balance Sheet'!H20
A12: Other Operating Changes | F12: 0 | G12: 0 | H12: 0 | I12: 0
A13: Cash from Operations (CFO) | B13: 2940 | C13: 5140 | D13: 7918 | E13: 9500 | F13: =F5+F6+F7 | G13: =G5+G6+G7 | H13: =H5+H6+H7 | I13: =I5+I6+I7
A15: INVESTING ACTIVITIES
A16: (-) Capital Expenditures | B16: 509 | C16: 860 | D16: 1221 | E16: 1230 | F16: ='Income Statement'!F4*Assumptions!F13 | G16: ='Income Statement'!G4*Assumptions!G13 | H16: ='Income Statement'!H4*Assumptions!H13 | I16: ='Income Statement'!I4*Assumptions!I13
A17: (-) Net Investment Changes | B17: -3362 | C17: -2590 | D17: -7066 | E17: -8570 | F17: =-('Balance Sheet'!F6-'Balance Sheet'!E6)-('Balance Sheet'!F14-'Balance Sheet'!E14) | G17: =-('Balance Sheet'!G6-'Balance Sheet'!F6)-('Balance Sheet'!G14-'Balance Sheet'!F14) | H17: =-('Balance Sheet'!H6-'Balance Sheet'!G6)-('Balance Sheet'!H14-'Balance Sheet'!G14) | I17: =-('Balance Sheet'!I6-'Balance Sheet'!H6)-('Balance Sheet'!I14-'Balance Sheet'!H14)
A18: Cash from Investing (CFI) | B18: =-B16+B17 | C18: =-C16+C17 | D18: =-D16+D17 | E18: =-E16+E17 | F18: =-F16+F17 | G18: =-G16+G17 | H18: =-H16+H17 | I18: =-I16+I17
A20: FINANCING ACTIVITIES
A21: Net Change in Cash | B21: =B13+B18 | C21: =C13+C18 | D21: =D13+D18 | E21: =E13+E18 | F21: =F13+F18 | G21: =G13+G18 | H21: =H13+H18 | I21: =I13+I18
