Workbook

Sheet Assumptions
A1: Key Assumptions � UBER (Uber Technologies) [UPDATED POST Q4-2025]
B3: 2023A | C3: 2024A | D3: 2025A | E3: 2026E | F3: 2027E | G3: 2028E | H3: 2029E
A4: Revenue Growth % | B4: 0.143 | C4: 0.177 | D4: 0.183 | E4: 0.178 | F4: 0.155 | G4: 0.136 | H4: 0.109
A5: COGS % of Revenue | B5: 0.632 | C5: 0.625 | D5: 0.618 | E5: 0.615 | F5: 0.608 | G5: 0.6 | H5: 0.592
A6: S&M % of Revenue | B6: 0.125 | C6: 0.115 | D6: 0.108 | E6: 0.11 | F6: 0.105 | G6: 0.1 | H6: 0.095
A7: R&D % of Revenue | B7: 0.126 | C7: 0.12 | D7: 0.117 | E7: 0.115 | F7: 0.11 | G7: 0.105 | H7: 0.1
A8: G&A % of Revenue | B8: 0.06 | C8: 0.055 | D8: 0.053 | E8: 0.052 | F8: 0.05 | G8: 0.048 | H8: 0.045
A9: D&A % of Revenue | B9: 0.02 | C9: 0.02 | D9: 0.02 | E9: 0.02 | F9: 0.02 | G9: 0.02 | H9: 0.02
A10: Tax Rate | B10: 0.15 | C10: 0.18 | D10: 0.2 | E10: 0.21 | F10: 0.21 | G10: 0.21 | H10: 0.21
A12: Capex % of Revenue | B12: 0.02 | C12: 0.022 | D12: 0.022 | E12: 0.022 | F12: 0.023 | G12: 0.023 | H12: 0.023
A13: AR Days | B13: 22 | C13: 20 | D13: 19 | E13: 19 | F13: 18 | G13: 18 | H13: 17
A14: AP Days | B14: 32 | C14: 30 | D14: 28 | E14: 27 | F14: 26 | G14: 25 | H14: 25
A15: Accrued Liabilities % Rev | B15: 0.08 | C15: 0.078 | D15: 0.075 | E15: 0.073 | F15: 0.07 | G15: 0.068 | H15: 0.065
A17: Interest Rate on Debt | B17: 0.05 | C17: 0.05 | D17: 0.048 | E17: 0.048 | F17: 0.046 | G17: 0.044 | H17: 0.042
A18: Shares Outstanding (M) | B18: 2052 | C18: 2068 | D18: 2084 | E18: 2042 | F18: 2000 | G18: 1960 | H18: 1920

Sheet Income Statement
A1: Income Statement � UBER ($M) [UPDATED POST Q4-2025]
B3: 2023A | C3: 2024A | D3: 2025A | E3: 2026E | F3: 2027E | G3: 2028E | H3: 2029E
A4: Revenue | B4: 37281 | C4: 43953 | D4: 52020 | E4: =D4*(1+Assumptions!E4) | F4: =E4*(1+Assumptions!F4) | G4: =F4*(1+Assumptions!G4) | H4: =G4*(1+Assumptions!H4)
A5: YoY Growth % | B5: 0.143 | C5: =(C4-B4)/B4 | D5: =(D4-C4)/C4 | E5: =Assumptions!E4 | F5: =Assumptions!F4 | G5: =Assumptions!G4 | H5: =Assumptions!H4
A6: (-) Cost of Revenue | B6: 23567 | C6: 27471 | D6: 32149 | E6: =E4*Assumptions!E5 | F6: =F4*Assumptions!F5 | G6: =G4*Assumptions!G5 | H6: =H4*Assumptions!H5
A7: Gross Profit | B7: =B4-B6 | C7: =C4-C6 | D7: =D4-D6 | E7: =E4-E6 | F7: =F4-F6 | G7: =G4-G6 | H7: =H4-H6
A8: Gross Margin % | B8: =B7/B4 | C8: =C7/C4 | D8: =D7/D4 | E8: =E7/E4 | F8: =F7/F4 | G8: =G7/G4 | H8: =H7/H4
A10: (-) Sales & Marketing | B10: 4661 | C10: 5055 | D10: 5618 | E10: =E4*Assumptions!E6 | F10: =F4*Assumptions!F6 | G10: =G4*Assumptions!G6 | H10: =H4*Assumptions!H6
A11: (-) Research & Development | B11: 4698 | C11: 5274 | D11: 6086 | E11: =E4*Assumptions!E7 | F11: =F4*Assumptions!F7 | G11: =G4*Assumptions!G7 | H11: =H4*Assumptions!H7
A12: (-) General & Administrative | B12: 2238 | C12: 2418 | D12: 2757 | E12: =E4*Assumptions!E8 | F12: =F4*Assumptions!F8 | G12: =G4*Assumptions!G8 | H12: =H4*Assumptions!H8
A13: Total Operating Expenses | B13: =B10+B11+B12 | C13: =C10+C11+C12 | D13: =D10+D11+D12 | E13: =E10+E11+E12 | F13: =F10+F11+F12 | G13: =G10+G11+G12 | H13: =H10+H11+H12
A15: Operating Income (EBIT) | B15: =B7-B13 | C15: =C7-C13 | D15: =D7-D13 | E15: =E7-E13 | F15: =F7-F13 | G15: =G7-G13 | H15: =H7-H13
A16: Operating Margin % | B16: =B15/B4 | C16: =C15/C4 | D16: =D15/D4 | E16: =E15/E4 | F16: =F15/F4 | G16: =G15/G4 | H16: =H15/H4
A18: (-) Interest Expense | B18: 465 | C18: 475 | D18: 456 | E18: ='Balance Sheet'!E14*Assumptions!E17 | F18: ='Balance Sheet'!F14*Assumptions!F17 | G18: ='Balance Sheet'!G14*Assumptions!G17 | H18: ='Balance Sheet'!H14*Assumptions!H17
A19: (+) Other Income / (Expense) | B19: -600 | C19: 1800 | D19: 900 | E19: 500 | F19: 500 | G19: 500 | H19: 500
A20: Pre-Tax Income | B20: =B15-B18+B19 | C20: =C15-C18+C19 | D20: =D15-D18+D19 | E20: =E15-E18+E19 | F20: =F15-F18+F19 | G20: =G15-G18+G19 | H20: =H15-H18+H19
A21: (-) Income Tax | B21: =B20*Assumptions!B10 | C21: =C20*Assumptions!C10 | D21: =D20*Assumptions!D10 | E21: =E20*Assumptions!E10 | F21: =F20*Assumptions!F10 | G21: =G20*Assumptions!G10 | H21: =H20*Assumptions!H10
A22: Effective Tax Rate | B22: =IF(B20=0,0,B21/B20) | C22: =IF(C20=0,0,C21/C20) | D22: =IF(D20=0,0,D21/D20) | E22: =IF(E20=0,0,E21/E20) | F22: =IF(F20=0,0,F21/F20) | G22: =IF(G20=0,0,G21/G20) | H22: =IF(H20=0,0,H21/H20)
A23: Net Income | B23: =B20-B21 | C23: =C20-C21 | D23: =D20-D21 | E23: =E20-E21 | F23: =F20-F21 | G23: =G20-G21 | H23: =H20-H21
A24: Net Margin % | B24: =B23/B4 | C24: =C23/C4 | D24: =D23/D4 | E24: =E23/E4 | F24: =F23/F4 | G24: =G23/G4 | H24: =H23/H4
A26: EPS (Diluted) | B26: =B23/Assumptions!B18 | C26: =C23/Assumptions!C18 | D26: =D23/Assumptions!D18 | E26: =E23/Assumptions!E18 | F26: =F23/Assumptions!F18 | G26: =G23/Assumptions!G18 | H26: =H23/Assumptions!H18
A27: EBITDA | B27: =B15+B4*Assumptions!B9 | C27: =C15+C4*Assumptions!C9 | D27: =D15+D4*Assumptions!D9 | E27: =E15+E4*Assumptions!E9 | F27: =F15+F4*Assumptions!F9 | G27: =G15+G4*Assumptions!G9 | H27: =H15+H4*Assumptions!H9
A28: EBITDA Margin % | B28: =B27/B4 | C28: =C27/C4 | D28: =D27/D4 | E28: =E27/E4 | F28: =F27/F4 | G28: =G27/G4 | H28: =H27/H4

Sheet Balance Sheet
A1: Balance Sheet � UBER ($M) [UPDATED POST Q4-2025]
B3: 2023A | C3: 2024A | D3: 2025A | E3: 2026E | F3: 2027E | G3: 2028E | H3: 2029E
A4: ASSETS
A5: Cash & Equivalents | B5: 5088 | C5: 5700 | D5: 7000 | E5: =D5+'Cash Flow'!E19 | F5: =E5+'Cash Flow'!F19 | G5: =F5+'Cash Flow'!G19 | H5: =G5+'Cash Flow'!H19
A6: Short-Term Investments | B6: 900 | C6: 1000 | D6: 1200 | E6: =D6*1.05 | F6: =E6*1.05 | G6: =F6*1.05 | H6: =G6*1.05
A7: Accounts Receivable | B7: 2249 | C7: 2403 | D7: 2708 | E7: ='Income Statement'!E4*Assumptions!E13/365 | F7: ='Income Statement'!F4*Assumptions!F13/365 | G7: ='Income Statement'!G4*Assumptions!G13/365 | H7: ='Income Statement'!H4*Assumptions!H13/365
A8: Other Current Assets | B8: 1800 | C8: 2000 | D8: 2300 | E8: =D8*1.05 | F8: =E8*1.05 | G8: =F8*1.05 | H8: =G8*1.05
A9: Total Current Assets | B9: =SUM(B5:B8) | C9: =SUM(C5:C8) | D9: =SUM(D5:D8) | E9: =SUM(E5:E8) | F9: =SUM(F5:F8) | G9: =SUM(G5:G8) | H9: =SUM(H5:H8)
A11: PP&E (net) | B11: 2095 | C11: 2300 | D11: 2600 | E11: =D11+'Income Statement'!E4*Assumptions!E12-'Income Statement'!E4*Assumptions!E9 | F11: =E11+'Income Statement'!F4*Assumptions!F12-'Income Statement'!F4*Assumptions!F9 | G11: =F11+'Income Statement'!G4*Assumptions!G12-'Income Statement'!G4*Assumptions!G9 | H11: =G11+'Income Statement'!H4*Assumptions!H12-'Income Statement'!H4*Assumptions!H9
A12: Goodwill | B12: 16100 | C12: 16300 | D12: 16300 | E12: =D12 | F12: =E12 | G12: =F12 | H12: =G12
A13: Equity Investments | B13: 13800 | C13: 15000 | D13: 15000 | E13: =D13 | F13: =E13 | G13: =F13 | H13: =G13
A14: Long-Term Debt | B14: 9459 | C14: 9500 | D14: 9500 | E14: =D14 | F14: =E14 | G14: =F14 | H14: =G14
A15: Other Non-Current Assets | B15: 3200 | C15: 3500 | D15: 3800 | E15: =D15*1.03 | F15: =E15*1.03 | G15: =F15*1.03 | H15: =G15*1.03
A16: Total Assets | B16: =B9+B11+B12+B13+B14+B15 | C16: =C9+C11+C12+C13+C14+C15 | D16: =D9+D11+D12+D13+D14+D15 | E16: =E9+E11+E12+E13+E14+E15 | F16: =F9+F11+F12+F13+F14+F15 | G16: =G9+G11+G12+G13+G14+G15 | H16: =H9+H11+H12+H13+H14+H15
A18: LIABILITIES
A19: Accounts Payable | B19: 1900 | C19: 2050 | D19: 2350 | E19: ='Income Statement'!E6*Assumptions!E14/365 | F19: ='Income Statement'!F6*Assumptions!F14/365 | G19: ='Income Statement'!G6*Assumptions!G14/365 | H19: ='Income Statement'!H6*Assumptions!H14/365
A20: Accrued Liabilities | B20: 2985 | C20: 3432 | D20: 3903 | E20: ='Income Statement'!E4*Assumptions!E15 | F20: ='Income Statement'!F4*Assumptions!F15 | G20: ='Income Statement'!G4*Assumptions!G15 | H20: ='Income Statement'!H4*Assumptions!H15
A21: Short-Term Debt | B21: 500 | C21: 500 | D21: 500 | E21: =D21 | F21: =E21 | G21: =F21 | H21: =G21
A22: Other Current Liabilities | B22: 3000 | C22: 3200 | D22: 3500 | E22: =D22*1.03 | F22: =E22*1.03 | G22: =F22*1.03 | H22: =G22*1.03
A23: Total Current Liabilities | B23: =SUM(B19:B22) | C23: =SUM(C19:C22) | D23: =SUM(D19:D22) | E23: =SUM(E19:E22) | F23: =SUM(F19:F22) | G23: =SUM(G19:G22) | H23: =SUM(H19:H22)
A25: Long-Term Debt | B25: 9459 | C25: 9500 | D25: 9500 | E25: =D25 | F25: =E25 | G25: =F25 | H25: =G25
A26: Other Non-Current Liabilities | B26: 5000 | C26: 5200 | D26: 5400 | E26: =D26*1.02 | F26: =E26*1.02 | G26: =F26*1.02 | H26: =G26*1.02
A27: Total Liabilities | B27: =B23+B25+B26 | C27: =C23+C25+C26 | D27: =D23+D25+D26 | E27: =E23+E25+E26 | F27: =F23+F25+F26 | G27: =G23+G25+G26 | H27: =H23+H25+H26
A29: EQUITY
A30: Retained Earnings | B30: =B16-B27-B31 | C30: =C16-C27-C31 | D30: =D16-D27-D31 | E30: =D30+'Income Statement'!E23 | F30: =E30+'Income Statement'!F23 | G30: =F30+'Income Statement'!G23 | H30: =G30+'Income Statement'!H23
A31: Other Equity | B31: 20188 | C31: 23321 | D31: 28000 | E31: =D31 | F31: =E31 | G31: =F31 | H31: =G31
A32: Total Equity | B32: =B30+B31 | C32: =C30+C31 | D32: =D30+D31 | E32: =E30+E31 | F32: =F30+F31 | G32: =G30+G31 | H32: =H30+H31
A33: Total Liab. + Equity | B33: =B27+B32 | C33: =C27+C32 | D33: =D27+D32 | E33: =E27+E32 | F33: =F27+F32 | G33: =G27+G32 | H33: =H27+H32
A34: Balance Check (should be 0) | B34: =B16-B33 | C34: =C16-C33 | D34: =D16-D33 | E34: =E16-E33 | F34: =F16-F33 | G34: =G16-G33 | H34: =H16-H33

Sheet Cash Flow
A1: Cash Flow Statement � UBER ($M) [UPDATED POST Q4-2025]
B3: 2023A | C3: 2024A | D3: 2025A | E3: 2026E | F3: 2027E | G3: 2028E | H3: 2029E
A4: OPERATING ACTIVITIES
A5: Net Income | B5: ='Income Statement'!B23 | C5: ='Income Statement'!C23 | D5: ='Income Statement'!D23 | E5: ='Income Statement'!E23 | F5: ='Income Statement'!F23 | G5: ='Income Statement'!G23 | H5: ='Income Statement'!H23
A6: (+) Depreciation & Amortization | B6: ='Income Statement'!B4*Assumptions!B9 | C6: ='Income Statement'!C4*Assumptions!C9 | D6: ='Income Statement'!D4*Assumptions!D9 | E6: ='Income Statement'!E4*Assumptions!E9 | F6: ='Income Statement'!F4*Assumptions!F9 | G6: ='Income Statement'!G4*Assumptions!G9 | H6: ='Income Statement'!H4*Assumptions!H9
A7: Stock-Based Compensation | B7: 1900 | C7: 1800 | D7: 1700 | E7: 1500 | F7: 1500 | G7: 1500 | H7: 1500
A8: Changes in Working Capital | E8: =E9+E10+E11+E12 | F8: =F9+F10+F11+F12 | G8: =G9+G10+G11+G12 | H8: =H9+H10+H11+H12
A9: Change in AR | E9: =-('Balance Sheet'!E7-'Balance Sheet'!D7) | F9: =-('Balance Sheet'!F7-'Balance Sheet'!E7) | G9: =-('Balance Sheet'!G7-'Balance Sheet'!F7) | H9: =-('Balance Sheet'!H7-'Balance Sheet'!G7)
A10: Change in AP | E10: ='Balance Sheet'!E19-'Balance Sheet'!D19 | F10: ='Balance Sheet'!F19-'Balance Sheet'!E19 | G10: ='Balance Sheet'!G19-'Balance Sheet'!F19 | H10: ='Balance Sheet'!H19-'Balance Sheet'!G19
A11: Change in Accrued Liab | E11: ='Balance Sheet'!E20-'Balance Sheet'!D20 | F11: ='Balance Sheet'!F20-'Balance Sheet'!E20 | G11: ='Balance Sheet'!G20-'Balance Sheet'!F20 | H11: ='Balance Sheet'!H20-'Balance Sheet'!G20
A12: Other Operating Changes | E12: 0 | F12: 0 | G12: 0 | H12: 0
A13: Cash from Operations (CFO) | B13: 6867 | C13: 7490 | D13: 10100 | E13: =E5+E6+E7+E8 | F13: =F5+F6+F7+F8 | G13: =G5+G6+G7+G8 | H13: =H5+H6+H7+H8
A15: INVESTING ACTIVITIES
A16: (-) Capital Expenditures | B16: 620 | C16: 750 | D16: 900 | E16: ='Income Statement'!E4*Assumptions!E12 | F16: ='Income Statement'!F4*Assumptions!F12 | G16: ='Income Statement'!G4*Assumptions!G12 | H16: ='Income Statement'!H4*Assumptions!H12
A17: (-) Net Investment Changes | B17: -200 | C17: -200 | D17: -200 | E17: -200 | F17: -200 | G17: -200 | H17: -200
A18: Cash from Investing (CFI) | B18: =-B16+B17 | C18: =-C16+C17 | D18: =-D16+D17 | E18: =-E16+E17 | F18: =-F16+F17 | G18: =-G16+G17 | H18: =-H16+H17
A19: Net Change in Cash | B19: =B13+B18 | C19: =C13+C18 | D19: =D13+D18 | E19: =E13+E18 | F19: =F13+F18 | G19: =G13+G18 | H19: =H13+H18
